snippet/__init__.py
snippet/__version__.py
snippet/cmd.py
snippet/meta.py
snippet/serializer.py
snippet/storage.py
snippet/tracker.py
snippet/utils.py
snippet_manager-1.1.1.dist-info/METADATA
snippet_manager-1.1.1.dist-info/WHEEL
snippet_manager-1.1.1.dist-info/entry_points.txt
snippet_manager-1.1.1.dist-info/top_level.txt
snippet_manager-1.1.1.dist-info/RECORD
