Metadata-Version: 2.1
Name: snippet-manager
Version: 1.1.1
Summary: Manage development snippets.
Home-page: https://github.com/foxyblue/snippet
Author: S. Williams-Wynn
Author-email: s.williamswynn.mail@gmail.com
License: UNKNOWN
Platform: UNKNOWN
Requires-Python: >=3.6
Requires-Dist: click
Requires-Dist: vim-edit
